[
{
		"name": "Heal The Sheep",
		"uniques": ["Heal this unit by [90] HP", "Doing so will consume this opportunity to choose a Promotion"],
		"unitTypes": ["Land Sheep", "Water Sheep", "Air Sheep", "Airborne Sheep", "Ram Sheep"],
	},
{
		"name": "March",
		"prerequisites": ["Accuracy II","Barrage II","Shock III","Drill III","Herd II","Reaping"],
		"uniques": ["Unit will heal every turn, even if it performs an action"],
		"unitTypes": ["Sword","Gunpowder","Archery","Ranged Gunpowder","Siege","Mounted", "Land Sheep", "Water Sheep", "Air Sheep", "Airborne Sheep"],
	},
{
"name": "Herd I",
"uniques": ["[+20]% Strength"],
"unitTypes": ["Land Sheep", "Water Sheep", "Air Sheep", "Airborne Sheep"],
},
{
"name": "Herd II",
"prerequisites": ["Herd I"],
"uniques": ["[+25]% Strength"],
"unitTypes": ["Land Sheep", "Water Sheep", "Air Sheep", "Airborne Sheep"],
},
{
"name": "Haycutting",
"prerequisites": ["Haycutting"],
"uniques": ["[+10]% Strength <vs [Mounted] units>", "Access to Reaper promotions"],
"unitTypes": ["Land Sheep"],
},
{
"name": "Harvesting",
"prerequisites": ["Haycutting"],
"uniques": ["Heals [10] damage if it kills a unit", "No movement cost to pillage"],
"unitTypes": ["Land Sheep"],
},
{
"name": "Reaping",
"prerequisites": ["Harvesting"],
"uniques": ["Heals [20] damage if it kills a unit", "[+50]% Strength <vs [Wounded] units><when attacking>"]
"unitTypes": ["Land Sheep"],
},
////////Ram////////
{"name": "Widder",
"prerequisites": ["Horns II"],
"uniques": ["[-15]% Strength for enemy [Military] units in adjacent [Land] tiles", "[-5]% Strength for enemy [City] units in adjacent [All] tiles"]
"unitTypes": ["Ram Sheep"],
},
{
"name": "Charge",
"prerequisites": ["Shock II","Drill II","Horns II"],
"uniques": ["[+33]% Strength <vs [Wounded] units>"],
"unitTypes": ["Mounted","Armored","Ram Sheep"]
},
{
"name": "Horns I",
"uniques":["[+10]% Strength <when attacking>"],
"unitTypes": ["Ram Sheep"],
},
{
"name": "Horns II",
"prerequisites": ["Horns I"],
"uniques":["[+10]% Strength"],
"unitTypes": ["Ram Sheep"],
},
{
"name": "Horns III",
"prerequisites": ["Horns II"],
"uniques":["[+15]% Strength <when attacking>"],
"unitTypes": ["Ram Sheep"],
},
{
"name": "Restless Sprint",
"prerequisites": ["Horns III"],
"uniques":["[+1] Movement","Can move after attacking"],
"unitTypes": ["Ram Sheep"],
},
{
"name": "Greater Fury",
"prerequisites": ["Horns III"],
"uniques":["[1] additional attacks per turn","[Great General] is earned [100]% faster"],
"unitTypes": ["Ram Sheep"],
},


]
